wagtail_easyai/__init__.py
wagtail_easyai/admin.py
wagtail_easyai/apps.py
wagtail_easyai/wagtail_hooks.py
wagtail_easyai/blocks/__init__.py
wagtail_easyai/blocks/graph.py
wagtail_easyai/blocks/ml.py
wagtail_easyai/migrations/0001_initial.py
wagtail_easyai/migrations/0002_auto_20210417_0513.py
wagtail_easyai/migrations/__init__.py
wagtail_easyai/models/__init__.py
wagtail_easyai/models/data.py
wagtail_easyai/models/project.py
wagtail_easyai/templates/wagtail_easyai/inspect.html
wagtail_easyai/templates/wagtail_easyai/predict.html
wagtail_easyai/templates/wagtail_easyai/train.html
wagtail_easyai/views/__init__.py
wagtail_easyai/views/pipeline.py
wagtail_easyai/widgets/__init__.py
wagtail_easyai/widgets/pipeline.py
wagtail_easyai/widgets/project.py
wagtail_easyAI-0.0.1.dist-info/LICENSE
wagtail_easyAI-0.0.1.dist-info/METADATA
wagtail_easyAI-0.0.1.dist-info/WHEEL
wagtail_easyAI-0.0.1.dist-info/top_level.txt
wagtail_easyAI-0.0.1.dist-info/RECORD
