Metadata-Version: 2.1
Name: wagtail-easyAI
Version: 0.0.1
Summary: Automated machine learning for Wagtail CMS
Home-page: https://github.com/whatyouseeiswhatyoulearn/wagtail-easyAI
Author: Finn Burmeister-Morton
License: GPL 3
Keywords: wagtail machine-learning automl
Platform: UNKNOWN
Classifier: Development Status :: 1 - Planning
Classifier: Intended Audience :: Developers
Classifier: License :: OSI Approved :: GNU General Public License v3 or later (GPLv3+)
Classifier: Operating System :: OS Independent
Classifier: Programming Language :: Python :: 3 :: Only
Classifier: Framework :: Django :: 3.1
Classifier: Framework :: Wagtail :: 2
Requires-Python: >=3.5
Requires-Dist: Wagtail (<3,>=2.4)
Requires-Dist: TPOT (>=0.11)
Requires-Dist: wagtail-generic-chooser (>=0.1.0)
